qleda/__init__.py
qleda/constants.py
qleda/common/__init__.py
qleda/common/electrical.py
qleda/common/papersize.py
qleda/common/units.py
qleda/controller/__init__.py
qleda/controller/library.py
qleda/controller/queries.py
qleda/controller/schematic.py
qleda/controller/test/__init__.py
qleda/controller/test/test_controller.py
qleda/core/__init__.py
qleda/core/dbbase.py
qleda/core/dbnamedtuple.py
qleda/core/dbsetup.py
qleda/core/mixins.py
qleda/core/point.py
qleda/core/testing.py
qleda/core/test/__init__.py
qleda/core/test/test_dbnamedtuple.py
qleda/core/test/test_point.py
qleda/drawing/__init__.py
qleda/drawing/boundaries.py
qleda/drawing/cairoexport.py
qleda/drawing/cairohelper.py
qleda/drawing/collections.py
qleda/drawing/dbdrawingcontainers.py
qleda/drawing/dbdrawingpieces.py
qleda/drawing/drawingmixins.py
qleda/drawing/drawingpieces.py
qleda/drawing/helper.py
qleda/drawing/textcolordefs.py
qleda/drawing/test/__init__.py
qleda/drawing/test/test_arc.py
qleda/drawing/test/test_dbdrawingcontainer.py
qleda/drawing/test/test_dbdrawingpieces.py
qleda/drawing/test/test_drawinggroup.py
qleda/drawing/test/test_drawingpieces.py
qleda/model/__init__.py
qleda/model/basic.py
qleda/model/schmodel.py
qleda/model/test/__init__.py
qleda/model/test/test_basic.py
qleda/model/test/test_schmodel.py
qleda/pypads/__init__.py
qleda/pypads/collection.py
qleda/pypads/constants.py
qleda/pypads/filehandler.py
qleda/pypads/filestructures.py
qleda/pypads/importer.py
qleda/pypads/padshelper.py
qleda/pypads/test/__init__.py
qleda/pypads/test/test_collection.py
qleda/pypads/test/test_importer.py
qleda/validation/__init__.py
qleda/validation/decorators.py
qleda/validation/exceptions.py
qleda/validation/functions.py
qleda/validation/test/__init__.py
qleda/validation/test/test_functions.py
qleda-0.1.3.dist-info/LICENSE
qleda-0.1.3.dist-info/METADATA
qleda-0.1.3.dist-info/WHEEL
qleda-0.1.3.dist-info/top_level.txt
qleda-0.1.3.dist-info/RECORD
