Metadata-Version: 2.1
Name: qleda
Version: 0.1.3
Summary: QLEDA is a python project to read or create schematics and netlists
Home-page: https://gitlab.com/locher/qleda
Author: René Locher
Author-email: rene_locher@hotmail.com
License: UNKNOWN
Platform: UNKNOWN
Classifier: Programming Language :: Python :: 3
Classifier: License :: OSI Approved :: GNU Lesser General Public License v3 or later (LGPLv3+)
Classifier: Operating System :: OS Independent
Requires-Python: >=3.9
Requires-Dist: numpy (>=1.19.4)
Requires-Dist: pycairo (>=1.20.0)
Requires-Dist: SQLAlchemy (>=1.3.0)
